whitebox/__init__.py
whitebox/automation.py
whitebox/cli.py
whitebox/download_wbt.py
whitebox/example.py
whitebox/whitebox.py
whitebox/whitebox_example.py
whitebox/whitebox_tools.py
whitebox-2.3.5.dist-info/AUTHORS.rst
whitebox-2.3.5.dist-info/LICENSE
whitebox-2.3.5.dist-info/METADATA
whitebox-2.3.5.dist-info/WHEEL
whitebox-2.3.5.dist-info/entry_points.txt
whitebox-2.3.5.dist-info/top_level.txt
whitebox-2.3.5.dist-info/RECORD
