Metadata-Version: 2.1
Name: whitebox
Version: 2.3.5
Summary: An advanced geospatial data analysis platform 
Home-page: https://github.com/opengeos/whitebox-python
Author: Qiusheng Wu
Author-email: giswqs@gmail.com
License: MIT license
Keywords: whitebox
Classifier: Development Status :: 2 - Pre-Alpha
Classifier: Intended Audience :: Developers
Classifier: License :: OSI Approved :: MIT License
Classifier: Natural Language :: English
Classifier: Programming Language :: Python :: 3
Classifier: Programming Language :: Python :: 3.4
Classifier: Programming Language :: Python :: 3.5
Classifier: Programming Language :: Python :: 3.6
License-File: LICENSE
License-File: AUTHORS.rst
Requires-Dist: Click>=6.0
